paretoset/__init__.py
paretoset/algorithms_numba.py
paretoset/algorithms_numpy.py
paretoset/user_interface.py
paretoset/utils.py
paretoset/tests/test_algorithms.py
paretoset/tests/test_api.py
paretoset-1.2.5.dist-info/licenses/LICENSE
paretoset-1.2.5.dist-info/METADATA
paretoset-1.2.5.dist-info/WHEEL
paretoset-1.2.5.dist-info/top_level.txt
paretoset-1.2.5.dist-info/RECORD
